thesaurus.py
cli_thesaurus-1.0.0b5.dist-info/LICENSE
cli_thesaurus-1.0.0b5.dist-info/METADATA
cli_thesaurus-1.0.0b5.dist-info/WHEEL
cli_thesaurus-1.0.0b5.dist-info/entry_points.txt
cli_thesaurus-1.0.0b5.dist-info/top_level.txt
cli_thesaurus-1.0.0b5.dist-info/RECORD
