Metadata-Version: 2.1
Name: cli-thesaurus
Version: 1.0.0b5
Summary: A command-line interface thesaurus
Home-page: https://github.com/sheatsley/thesaurus
Author: Ryan Sheatsley
Author-email: ryan@sheatsley.me
License: MIT
Keywords: cli command-line terminal thesaurus
Platform: UNKNOWN
Classifier: Development Status :: 4 - Beta
Classifier: License :: OSI Approved :: MIT License
Classifier: Operating System :: OS Independent
Classifier: Programming Language :: Python :: 3
Classifier: Topic :: Education
Classifier: Topic :: Terminals
Requires-Python: >=3
Requires-Dist: requests
